<?xml version="1.0" encoding="UTF-8"?>
<con:soapui-project id="d8a4ab1b-d3a1-4c26-8bfb-ad36bce0b9c1" activeEnvironment="Default" name="CountryInfoService" resourceRoot="" soapui-version="5.4.0" xmlns:con="http://eviware.com/soapui/config"><con:settings/><con:interface xsi:type="con:WsdlInterface" id="b3a0f243-faba-429f-810e-0dd03f5968d6" wsaVersion="NONE" name="CountryInfoServiceSoapBinding" type="wsdl" bindingName="{http://www.oorsprong.org/websamples.countryinfo}CountryInfoServiceSoapBinding" soapVersion="1_1" anonymous="optional" definition="http://www.oorsprong.org/websamples.countryinfo/CountryInfoService.wso?WSDL" xmlns:xsi="http://www.w3.org/2001/XMLSchema-instance"><con:settings><con:setting id="CreateWsdlDocumentationAction@report-directory">/Users/Guest/Documents</con:setting></con:settings><con:definitionCache type="TEXT" rootPart="http://www.oorsprong.org/websamples.countryinfo/CountryInfoService.wso?WSDL"><con:part><con:url>http://www.oorsprong.org/websamples.countryinfo/CountryInfoService.wso?WSDL</con:url><con:content><![CDATA[<definitions name="CountryInfoService" targetNamespace="http://www.oorsprong.org/websamples.countryinfo" xmlns="http://schemas.xmlsoap.org/wsdl/" xmlns:xs="http://www.w3.org/2001/XMLSchema" xmlns:soap="http://schemas.xmlsoap.org/wsdl/soap/" xmlns:soap12="http://schemas.xmlsoap.org/wsdl/soap12/" xmlns:tns="http://www.oorsprong.org/websamples.countryinfo">
  <types>
    <xs:schema elementFormDefault="qualified" targetNamespace="http://www.oorsprong.org/websamples.countryinfo">
      <xs:complexType name="tContinent">
        <xs:sequence>
          <xs:element name="sCode" type="xs:string"/>
          <xs:element name="sName" type="xs:string"/>
        </xs:sequence>
      </xs:complexType>
      <xs:complexType name="tCurrency">
        <xs:sequence>
          <xs:element name="sISOCode" type="xs:string"/>
          <xs:element name="sName" type="xs:string"/>
        </xs:sequence>
      </xs:complexType>
      <xs:complexType name="tCountryCodeAndName">
        <xs:sequence>
          <xs:element name="sISOCode" type="xs:string"/>
          <xs:element name="sName" type="xs:string"/>
        </xs:sequence>
      </xs:complexType>
      <xs:complexType name="tCountryCodeAndNameGroupedByContinent">
        <xs:sequence>
          <xs:element name="Continent" type="tns:tContinent"/>
          <xs:element name="CountryCodeAndNames" type="tns:ArrayOftCountryCodeAndName"/>
        </xs:sequence>
      </xs:complexType>
      <xs:complexType name="tCountryInfo">
        <xs:sequence>
          <xs:element name="sISOCode" type="xs:string"/>
          <xs:element name="sName" type="xs:string"/>
          <xs:element name="sCapitalCity" type="xs:string"/>
          <xs:element name="sPhoneCode" type="xs:string"/>
          <xs:element name="sContinentCode" type="xs:string"/>
          <xs:element name="sCurrencyISOCode" type="xs:string"/>
          <xs:element name="sCountryFlag" type="xs:string"/>
          <xs:element name="Languages" type="tns:ArrayOftLanguage"/>
        </xs:sequence>
      </xs:complexType>
      <xs:complexType name="tLanguage">
        <xs:sequence>
          <xs:element name="sISOCode" type="xs:string"/>
          <xs:element name="sName" type="xs:string"/>
        </xs:sequence>
      </xs:complexType>
      <xs:complexType name="ArrayOftCountryCodeAndName">
        <xs:sequence>
          <xs:element name="tCountryCodeAndName" type="tns:tCountryCodeAndName" minOccurs="0" maxOccurs="unbounded" nillable="true"/>
        </xs:sequence>
      </xs:complexType>
      <xs:complexType name="ArrayOftLanguage">
        <xs:sequence>
          <xs:element name="tLanguage" type="tns:tLanguage" minOccurs="0" maxOccurs="unbounded" nillable="true"/>
        </xs:sequence>
      </xs:complexType>
      <xs:complexType name="ArrayOftContinent">
        <xs:sequence>
          <xs:element name="tContinent" type="tns:tContinent" minOccurs="0" maxOccurs="unbounded" nillable="true"/>
        </xs:sequence>
      </xs:complexType>
      <xs:complexType name="ArrayOftCurrency">
        <xs:sequence>
          <xs:element name="tCurrency" type="tns:tCurrency" minOccurs="0" maxOccurs="unbounded" nillable="true"/>
        </xs:sequence>
      </xs:complexType>
      <xs:complexType name="ArrayOftCountryCodeAndNameGroupedByContinent">
        <xs:sequence>
          <xs:element name="tCountryCodeAndNameGroupedByContinent" type="tns:tCountryCodeAndNameGroupedByContinent" minOccurs="0" maxOccurs="unbounded" nillable="true"/>
        </xs:sequence>
      </xs:complexType>
      <xs:complexType name="ArrayOftCountryInfo">
        <xs:sequence>
          <xs:element name="tCountryInfo" type="tns:tCountryInfo" minOccurs="0" maxOccurs="unbounded" nillable="true"/>
        </xs:sequence>
      </xs:complexType>
      <xs:element name="ListOfContinentsByName">
        <xs:complexType>
          <xs:sequence/>
        </xs:complexType>
      </xs:element>
      <xs:element name="ListOfContinentsByNameResponse">
        <xs:complexType>
          <xs:sequence>
            <xs:element name="ListOfContinentsByNameResult" type="tns:ArrayOftContinent"/>
          </xs:sequence>
        </xs:complexType>
      </xs:element>
      <xs:element name="ListOfContinentsByCode">
        <xs:complexType>
          <xs:sequence/>
        </xs:complexType>
      </xs:element>
      <xs:element name="ListOfContinentsByCodeResponse">
        <xs:complexType>
          <xs:sequence>
            <xs:element name="ListOfContinentsByCodeResult" type="tns:ArrayOftContinent"/>
          </xs:sequence>
        </xs:complexType>
      </xs:element>
      <xs:element name="ListOfCurrenciesByName">
        <xs:complexType>
          <xs:sequence/>
        </xs:complexType>
      </xs:element>
      <xs:element name="ListOfCurrenciesByNameResponse">
        <xs:complexType>
          <xs:sequence>
            <xs:element name="ListOfCurrenciesByNameResult" type="tns:ArrayOftCurrency"/>
          </xs:sequence>
        </xs:complexType>
      </xs:element>
      <xs:element name="ListOfCurrenciesByCode">
        <xs:complexType>
          <xs:sequence/>
        </xs:complexType>
      </xs:element>
      <xs:element name="ListOfCurrenciesByCodeResponse">
        <xs:complexType>
          <xs:sequence>
            <xs:element name="ListOfCurrenciesByCodeResult" type="tns:ArrayOftCurrency"/>
          </xs:sequence>
        </xs:complexType>
      </xs:element>
      <xs:element name="CurrencyName">
        <xs:complexType>
          <xs:sequence>
            <xs:element name="sCurrencyISOCode" type="xs:string"/>
          </xs:sequence>
        </xs:complexType>
      </xs:element>
      <xs:element name="CurrencyNameResponse">
        <xs:complexType>
          <xs:sequence>
            <xs:element name="CurrencyNameResult" type="xs:string"/>
          </xs:sequence>
        </xs:complexType>
      </xs:element>
      <xs:element name="ListOfCountryNamesByCode">
        <xs:complexType>
          <xs:sequence/>
        </xs:complexType>
      </xs:element>
      <xs:element name="ListOfCountryNamesByCodeResponse">
        <xs:complexType>
          <xs:sequence>
            <xs:element name="ListOfCountryNamesByCodeResult" type="tns:ArrayOftCountryCodeAndName"/>
          </xs:sequence>
        </xs:complexType>
      </xs:element>
      <xs:element name="ListOfCountryNamesByName">
        <xs:complexType>
          <xs:sequence/>
        </xs:complexType>
      </xs:element>
      <xs:element name="ListOfCountryNamesByNameResponse">
        <xs:complexType>
          <xs:sequence>
            <xs:element name="ListOfCountryNamesByNameResult" type="tns:ArrayOftCountryCodeAndName"/>
          </xs:sequence>
        </xs:complexType>
      </xs:element>
      <xs:element name="ListOfCountryNamesGroupedByContinent">
        <xs:complexType>
          <xs:sequence/>
        </xs:complexType>
      </xs:element>
      <xs:element name="ListOfCountryNamesGroupedByContinentResponse">
        <xs:complexType>
          <xs:sequence>
            <xs:element name="ListOfCountryNamesGroupedByContinentResult" type="tns:ArrayOftCountryCodeAndNameGroupedByContinent"/>
          </xs:sequence>
        </xs:complexType>
      </xs:element>
      <xs:element name="CountryName">
        <xs:complexType>
          <xs:sequence>
            <xs:element name="sCountryISOCode" type="xs:string"/>
          </xs:sequence>
        </xs:complexType>
      </xs:element>
      <xs:element name="CountryNameResponse">
        <xs:complexType>
          <xs:sequence>
            <xs:element name="CountryNameResult" type="xs:string"/>
          </xs:sequence>
        </xs:complexType>
      </xs:element>
      <xs:element name="CountryISOCode">
        <xs:complexType>
          <xs:sequence>
            <xs:element name="sCountryName" type="xs:string"/>
          </xs:sequence>
        </xs:complexType>
      </xs:element>
      <xs:element name="CountryISOCodeResponse">
        <xs:complexType>
          <xs:sequence>
            <xs:element name="CountryISOCodeResult" type="xs:string"/>
          </xs:sequence>
        </xs:complexType>
      </xs:element>
      <xs:element name="CapitalCity">
        <xs:complexType>
          <xs:sequence>
            <xs:element name="sCountryISOCode" type="xs:string"/>
          </xs:sequence>
        </xs:complexType>
      </xs:element>
      <xs:element name="CapitalCityResponse">
        <xs:complexType>
          <xs:sequence>
            <xs:element name="CapitalCityResult" type="xs:string"/>
          </xs:sequence>
        </xs:complexType>
      </xs:element>
      <xs:element name="CountryCurrency">
        <xs:complexType>
          <xs:sequence>
            <xs:element name="sCountryISOCode" type="xs:string"/>
          </xs:sequence>
        </xs:complexType>
      </xs:element>
      <xs:element name="CountryCurrencyResponse">
        <xs:complexType>
          <xs:sequence>
            <xs:element name="CountryCurrencyResult" type="tns:tCurrency"/>
          </xs:sequence>
        </xs:complexType>
      </xs:element>
      <xs:element name="CountryFlag">
        <xs:complexType>
          <xs:sequence>
            <xs:element name="sCountryISOCode" type="xs:string"/>
          </xs:sequence>
        </xs:complexType>
      </xs:element>
      <xs:element name="CountryFlagResponse">
        <xs:complexType>
          <xs:sequence>
            <xs:element name="CountryFlagResult" type="xs:string"/>
          </xs:sequence>
        </xs:complexType>
      </xs:element>
      <xs:element name="CountryIntPhoneCode">
        <xs:complexType>
          <xs:sequence>
            <xs:element name="sCountryISOCode" type="xs:string"/>
          </xs:sequence>
        </xs:complexType>
      </xs:element>
      <xs:element name="CountryIntPhoneCodeResponse">
        <xs:complexType>
          <xs:sequence>
            <xs:element name="CountryIntPhoneCodeResult" type="xs:string"/>
          </xs:sequence>
        </xs:complexType>
      </xs:element>
      <xs:element name="FullCountryInfo">
        <xs:complexType>
          <xs:sequence>
            <xs:element name="sCountryISOCode" type="xs:string"/>
          </xs:sequence>
        </xs:complexType>
      </xs:element>
      <xs:element name="FullCountryInfoResponse">
        <xs:complexType>
          <xs:sequence>
            <xs:element name="FullCountryInfoResult" type="tns:tCountryInfo"/>
          </xs:sequence>
        </xs:complexType>
      </xs:element>
      <xs:element name="FullCountryInfoAllCountries">
        <xs:complexType>
          <xs:sequence/>
        </xs:complexType>
      </xs:element>
      <xs:element name="FullCountryInfoAllCountriesResponse">
        <xs:complexType>
          <xs:sequence>
            <xs:element name="FullCountryInfoAllCountriesResult" type="tns:ArrayOftCountryInfo"/>
          </xs:sequence>
        </xs:complexType>
      </xs:element>
      <xs:element name="CountriesUsingCurrency">
        <xs:complexType>
          <xs:sequence>
            <xs:element name="sISOCurrencyCode" type="xs:string"/>
          </xs:sequence>
        </xs:complexType>
      </xs:element>
      <xs:element name="CountriesUsingCurrencyResponse">
        <xs:complexType>
          <xs:sequence>
            <xs:element name="CountriesUsingCurrencyResult" type="tns:ArrayOftCountryCodeAndName"/>
          </xs:sequence>
        </xs:complexType>
      </xs:element>
      <xs:element name="ListOfLanguagesByName">
        <xs:complexType>
          <xs:sequence/>
        </xs:complexType>
      </xs:element>
      <xs:element name="ListOfLanguagesByNameResponse">
        <xs:complexType>
          <xs:sequence>
            <xs:element name="ListOfLanguagesByNameResult" type="tns:ArrayOftLanguage"/>
          </xs:sequence>
        </xs:complexType>
      </xs:element>
      <xs:element name="ListOfLanguagesByCode">
        <xs:complexType>
          <xs:sequence/>
        </xs:complexType>
      </xs:element>
      <xs:element name="ListOfLanguagesByCodeResponse">
        <xs:complexType>
          <xs:sequence>
            <xs:element name="ListOfLanguagesByCodeResult" type="tns:ArrayOftLanguage"/>
          </xs:sequence>
        </xs:complexType>
      </xs:element>
      <xs:element name="LanguageName">
        <xs:complexType>
          <xs:sequence>
            <xs:element name="sISOCode" type="xs:string"/>
          </xs:sequence>
        </xs:complexType>
      </xs:element>
      <xs:element name="LanguageNameResponse">
        <xs:complexType>
          <xs:sequence>
            <xs:element name="LanguageNameResult" type="xs:string"/>
          </xs:sequence>
        </xs:complexType>
      </xs:element>
      <xs:element name="LanguageISOCode">
        <xs:complexType>
          <xs:sequence>
            <xs:element name="sLanguageName" type="xs:string"/>
          </xs:sequence>
        </xs:complexType>
      </xs:element>
      <xs:element name="LanguageISOCodeResponse">
        <xs:complexType>
          <xs:sequence>
            <xs:element name="LanguageISOCodeResult" type="xs:string"/>
          </xs:sequence>
        </xs:complexType>
      </xs:element>
    </xs:schema>
  </types>
  <message name="ListOfContinentsByNameSoapRequest">
    <part name="parameters" element="tns:ListOfContinentsByName"/>
  </message>
  <message name="ListOfContinentsByNameSoapResponse">
    <part name="parameters" element="tns:ListOfContinentsByNameResponse"/>
  </message>
  <message name="ListOfContinentsByCodeSoapRequest">
    <part name="parameters" element="tns:ListOfContinentsByCode"/>
  </message>
  <message name="ListOfContinentsByCodeSoapResponse">
    <part name="parameters" element="tns:ListOfContinentsByCodeResponse"/>
  </message>
  <message name="ListOfCurrenciesByNameSoapRequest">
    <part name="parameters" element="tns:ListOfCurrenciesByName"/>
  </message>
  <message name="ListOfCurrenciesByNameSoapResponse">
    <part name="parameters" element="tns:ListOfCurrenciesByNameResponse"/>
  </message>
  <message name="ListOfCurrenciesByCodeSoapRequest">
    <part name="parameters" element="tns:ListOfCurrenciesByCode"/>
  </message>
  <message name="ListOfCurrenciesByCodeSoapResponse">
    <part name="parameters" element="tns:ListOfCurrenciesByCodeResponse"/>
  </message>
  <message name="CurrencyNameSoapRequest">
    <part name="parameters" element="tns:CurrencyName"/>
  </message>
  <message name="CurrencyNameSoapResponse">
    <part name="parameters" element="tns:CurrencyNameResponse"/>
  </message>
  <message name="ListOfCountryNamesByCodeSoapRequest">
    <part name="parameters" element="tns:ListOfCountryNamesByCode"/>
  </message>
  <message name="ListOfCountryNamesByCodeSoapResponse">
    <part name="parameters" element="tns:ListOfCountryNamesByCodeResponse"/>
  </message>
  <message name="ListOfCountryNamesByNameSoapRequest">
    <part name="parameters" element="tns:ListOfCountryNamesByName"/>
  </message>
  <message name="ListOfCountryNamesByNameSoapResponse">
    <part name="parameters" element="tns:ListOfCountryNamesByNameResponse"/>
  </message>
  <message name="ListOfCountryNamesGroupedByContinentSoapRequest">
    <part name="parameters" element="tns:ListOfCountryNamesGroupedByContinent"/>
  </message>
  <message name="ListOfCountryNamesGroupedByContinentSoapResponse">
    <part name="parameters" element="tns:ListOfCountryNamesGroupedByContinentResponse"/>
  </message>
  <message name="CountryNameSoapRequest">
    <part name="parameters" element="tns:CountryName"/>
  </message>
  <message name="CountryNameSoapResponse">
    <part name="parameters" element="tns:CountryNameResponse"/>
  </message>
  <message name="CountryISOCodeSoapRequest">
    <part name="parameters" element="tns:CountryISOCode"/>
  </message>
  <message name="CountryISOCodeSoapResponse">
    <part name="parameters" element="tns:CountryISOCodeResponse"/>
  </message>
  <message name="CapitalCitySoapRequest">
    <part name="parameters" element="tns:CapitalCity"/>
  </message>
  <message name="CapitalCitySoapResponse">
    <part name="parameters" element="tns:CapitalCityResponse"/>
  </message>
  <message name="CountryCurrencySoapRequest">
    <part name="parameters" element="tns:CountryCurrency"/>
  </message>
  <message name="CountryCurrencySoapResponse">
    <part name="parameters" element="tns:CountryCurrencyResponse"/>
  </message>
  <message name="CountryFlagSoapRequest">
    <part name="parameters" element="tns:CountryFlag"/>
  </message>
  <message name="CountryFlagSoapResponse">
    <part name="parameters" element="tns:CountryFlagResponse"/>
  </message>
  <message name="CountryIntPhoneCodeSoapRequest">
    <part name="parameters" element="tns:CountryIntPhoneCode"/>
  </message>
  <message name="CountryIntPhoneCodeSoapResponse">
    <part name="parameters" element="tns:CountryIntPhoneCodeResponse"/>
  </message>
  <message name="FullCountryInfoSoapRequest">
    <part name="parameters" element="tns:FullCountryInfo"/>
  </message>
  <message name="FullCountryInfoSoapResponse">
    <part name="parameters" element="tns:FullCountryInfoResponse"/>
  </message>
  <message name="FullCountryInfoAllCountriesSoapRequest">
    <part name="parameters" element="tns:FullCountryInfoAllCountries"/>
  </message>
  <message name="FullCountryInfoAllCountriesSoapResponse">
    <part name="parameters" element="tns:FullCountryInfoAllCountriesResponse"/>
  </message>
  <message name="CountriesUsingCurrencySoapRequest">
    <part name="parameters" element="tns:CountriesUsingCurrency"/>
  </message>
  <message name="CountriesUsingCurrencySoapResponse">
    <part name="parameters" element="tns:CountriesUsingCurrencyResponse"/>
  </message>
  <message name="ListOfLanguagesByNameSoapRequest">
    <part name="parameters" element="tns:ListOfLanguagesByName"/>
  </message>
  <message name="ListOfLanguagesByNameSoapResponse">
    <part name="parameters" element="tns:ListOfLanguagesByNameResponse"/>
  </message>
  <message name="ListOfLanguagesByCodeSoapRequest">
    <part name="parameters" element="tns:ListOfLanguagesByCode"/>
  </message>
  <message name="ListOfLanguagesByCodeSoapResponse">
    <part name="parameters" element="tns:ListOfLanguagesByCodeResponse"/>
  </message>
  <message name="LanguageNameSoapRequest">
    <part name="parameters" element="tns:LanguageName"/>
  </message>
  <message name="LanguageNameSoapResponse">
    <part name="parameters" element="tns:LanguageNameResponse"/>
  </message>
  <message name="LanguageISOCodeSoapRequest">
    <part name="parameters" element="tns:LanguageISOCode"/>
  </message>
  <message name="LanguageISOCodeSoapResponse">
    <part name="parameters" element="tns:LanguageISOCodeResponse"/>
  </message>
  <portType name="CountryInfoServiceSoapType">
    <operation name="ListOfContinentsByName">
      <documentation>Returns a list of continents ordered by name.</documentation>
      <input message="tns:ListOfContinentsByNameSoapRequest"/>
      <output message="tns:ListOfContinentsByNameSoapResponse"/>
    </operation>
    <operation name="ListOfContinentsByCode">
      <documentation>Returns a list of continents ordered by code.</documentation>
      <input message="tns:ListOfContinentsByCodeSoapRequest"/>
      <output message="tns:ListOfContinentsByCodeSoapResponse"/>
    </operation>
    <operation name="ListOfCurrenciesByName">
      <documentation>Returns a list of currencies ordered by name.</documentation>
      <input message="tns:ListOfCurrenciesByNameSoapRequest"/>
      <output message="tns:ListOfCurrenciesByNameSoapResponse"/>
    </operation>
    <operation name="ListOfCurrenciesByCode">
      <documentation>Returns a list of currencies ordered by code.</documentation>
      <input message="tns:ListOfCurrenciesByCodeSoapRequest"/>
      <output message="tns:ListOfCurrenciesByCodeSoapResponse"/>
    </operation>
    <operation name="CurrencyName">
      <documentation>Returns the name of the currency (if found)</documentation>
      <input message="tns:CurrencyNameSoapRequest"/>
      <output message="tns:CurrencyNameSoapResponse"/>
    </operation>
    <operation name="ListOfCountryNamesByCode">
      <documentation>Returns a list of all stored counties ordered by ISO code</documentation>
      <input message="tns:ListOfCountryNamesByCodeSoapRequest"/>
      <output message="tns:ListOfCountryNamesByCodeSoapResponse"/>
    </operation>
    <operation name="ListOfCountryNamesByName">
      <documentation>Returns a list of all stored counties ordered by country name</documentation>
      <input message="tns:ListOfCountryNamesByNameSoapRequest"/>
      <output message="tns:ListOfCountryNamesByNameSoapResponse"/>
    </operation>
    <operation name="ListOfCountryNamesGroupedByContinent">
      <documentation>Returns a list of all stored counties grouped per continent</documentation>
      <input message="tns:ListOfCountryNamesGroupedByContinentSoapRequest"/>
      <output message="tns:ListOfCountryNamesGroupedByContinentSoapResponse"/>
    </operation>
    <operation name="CountryName">
      <documentation>Searches the database for a country by the passed ISO country code</documentation>
      <input message="tns:CountryNameSoapRequest"/>
      <output message="tns:CountryNameSoapResponse"/>
    </operation>
    <operation name="CountryISOCode">
      <documentation>This function tries to found a country based on the passed country name.</documentation>
      <input message="tns:CountryISOCodeSoapRequest"/>
      <output message="tns:CountryISOCodeSoapResponse"/>
    </operation>
    <operation name="CapitalCity">
      <documentation>Returns the  name of the captial city for the passed country code</documentation>
      <input message="tns:CapitalCitySoapRequest"/>
      <output message="tns:CapitalCitySoapResponse"/>
    </operation>
    <operation name="CountryCurrency">
      <documentation>Returns the currency ISO code and name for the passed country ISO code</documentation>
      <input message="tns:CountryCurrencySoapRequest"/>
      <output message="tns:CountryCurrencySoapResponse"/>
    </operation>
    <operation name="CountryFlag">
      <documentation>Returns a link to a picture of the country flag</documentation>
      <input message="tns:CountryFlagSoapRequest"/>
      <output message="tns:CountryFlagSoapResponse"/>
    </operation>
    <operation name="CountryIntPhoneCode">
      <documentation>Returns the internation phone code for the passed ISO country code</documentation>
      <input message="tns:CountryIntPhoneCodeSoapRequest"/>
      <output message="tns:CountryIntPhoneCodeSoapResponse"/>
    </operation>
    <operation name="FullCountryInfo">
      <documentation>Returns a struct with all the stored country information. Pass the ISO country code</documentation>
      <input message="tns:FullCountryInfoSoapRequest"/>
      <output message="tns:FullCountryInfoSoapResponse"/>
    </operation>
    <operation name="FullCountryInfoAllCountries">
      <documentation>Returns an array with all countries and all the language information stored</documentation>
      <input message="tns:FullCountryInfoAllCountriesSoapRequest"/>
      <output message="tns:FullCountryInfoAllCountriesSoapResponse"/>
    </operation>
    <operation name="CountriesUsingCurrency">
      <documentation>Returns a list of all countries that use the same currency code. Pass a ISO currency code</documentation>
      <input message="tns:CountriesUsingCurrencySoapRequest"/>
      <output message="tns:CountriesUsingCurrencySoapResponse"/>
    </operation>
    <operation name="ListOfLanguagesByName">
      <documentation>Returns an array of languages ordered by name</documentation>
      <input message="tns:ListOfLanguagesByNameSoapRequest"/>
      <output message="tns:ListOfLanguagesByNameSoapResponse"/>
    </operation>
    <operation name="ListOfLanguagesByCode">
      <documentation>Returns an array of languages ordered by code</documentation>
      <input message="tns:ListOfLanguagesByCodeSoapRequest"/>
      <output message="tns:ListOfLanguagesByCodeSoapResponse"/>
    </operation>
    <operation name="LanguageName">
      <documentation>Find a language name based on the passed ISO language code</documentation>
      <input message="tns:LanguageNameSoapRequest"/>
      <output message="tns:LanguageNameSoapResponse"/>
    </operation>
    <operation name="LanguageISOCode">
      <documentation>Find a language ISO code based on the passed language name</documentation>
      <input message="tns:LanguageISOCodeSoapRequest"/>
      <output message="tns:LanguageISOCodeSoapResponse"/>
    </operation>
  </portType>
  <binding name="CountryInfoServiceSoapBinding" type="tns:CountryInfoServiceSoapType">
    <soap:binding style="document" transport="http://schemas.xmlsoap.org/soap/http"/>
    <operation name="ListOfContinentsByName">
      <soap:operation soapAction="" style="document"/>
      <input>
        <soap:body use="literal"/>
      </input>
      <output>
        <soap:body use="literal"/>
      </output>
    </operation>
    <operation name="ListOfContinentsByCode">
      <soap:operation soapAction="" style="document"/>
      <input>
        <soap:body use="literal"/>
      </input>
      <output>
        <soap:body use="literal"/>
      </output>
    </operation>
    <operation name="ListOfCurrenciesByName">
      <soap:operation soapAction="" style="document"/>
      <input>
        <soap:body use="literal"/>
      </input>
      <output>
        <soap:body use="literal"/>
      </output>
    </operation>
    <operation name="ListOfCurrenciesByCode">
      <soap:operation soapAction="" style="document"/>
      <input>
        <soap:body use="literal"/>
      </input>
      <output>
        <soap:body use="literal"/>
      </output>
    </operation>
    <operation name="CurrencyName">
      <soap:operation soapAction="" style="document"/>
      <input>
        <soap:body use="literal"/>
      </input>
      <output>
        <soap:body use="literal"/>
      </output>
    </operation>
    <operation name="ListOfCountryNamesByCode">
      <soap:operation soapAction="" style="document"/>
      <input>
        <soap:body use="literal"/>
      </input>
      <output>
        <soap:body use="literal"/>
      </output>
    </operation>
    <operation name="ListOfCountryNamesByName">
      <soap:operation soapAction="" style="document"/>
      <input>
        <soap:body use="literal"/>
      </input>
      <output>
        <soap:body use="literal"/>
      </output>
    </operation>
    <operation name="ListOfCountryNamesGroupedByContinent">
      <soap:operation soapAction="" style="document"/>
      <input>
        <soap:body use="literal"/>
      </input>
      <output>
        <soap:body use="literal"/>
      </output>
    </operation>
    <operation name="CountryName">
      <soap:operation soapAction="" style="document"/>
      <input>
        <soap:body use="literal"/>
      </input>
      <output>
        <soap:body use="literal"/>
      </output>
    </operation>
    <operation name="CountryISOCode">
      <soap:operation soapAction="" style="document"/>
      <input>
        <soap:body use="literal"/>
      </input>
      <output>
        <soap:body use="literal"/>
      </output>
    </operation>
    <operation name="CapitalCity">
      <soap:operation soapAction="" style="document"/>
      <input>
        <soap:body use="literal"/>
      </input>
      <output>
        <soap:body use="literal"/>
      </output>
    </operation>
    <operation name="CountryCurrency">
      <soap:operation soapAction="" style="document"/>
      <input>
        <soap:body use="literal"/>
      </input>
      <output>
        <soap:body use="literal"/>
      </output>
    </operation>
    <operation name="CountryFlag">
      <soap:operation soapAction="" style="document"/>
      <input>
        <soap:body use="literal"/>
      </input>
      <output>
        <soap:body use="literal"/>
      </output>
    </operation>
    <operation name="CountryIntPhoneCode">
      <soap:operation soapAction="" style="document"/>
      <input>
        <soap:body use="literal"/>
      </input>
      <output>
        <soap:body use="literal"/>
      </output>
    </operation>
    <operation name="FullCountryInfo">
      <soap:operation soapAction="" style="document"/>
      <input>
        <soap:body use="literal"/>
      </input>
      <output>
        <soap:body use="literal"/>
      </output>
    </operation>
    <operation name="FullCountryInfoAllCountries">
      <soap:operation soapAction="" style="document"/>
      <input>
        <soap:body use="literal"/>
      </input>
      <output>
        <soap:body use="literal"/>
      </output>
    </operation>
    <operation name="CountriesUsingCurrency">
      <soap:operation soapAction="" style="document"/>
      <input>
        <soap:body use="literal"/>
      </input>
      <output>
        <soap:body use="literal"/>
      </output>
    </operation>
    <operation name="ListOfLanguagesByName">
      <soap:operation soapAction="" style="document"/>
      <input>
        <soap:body use="literal"/>
      </input>
      <output>
        <soap:body use="literal"/>
      </output>
    </operation>
    <operation name="ListOfLanguagesByCode">
      <soap:operation soapAction="" style="document"/>
      <input>
        <soap:body use="literal"/>
      </input>
      <output>
        <soap:body use="literal"/>
      </output>
    </operation>
    <operation name="LanguageName">
      <soap:operation soapAction="" style="document"/>
      <input>
        <soap:body use="literal"/>
      </input>
      <output>
        <soap:body use="literal"/>
      </output>
    </operation>
    <operation name="LanguageISOCode">
      <soap:operation soapAction="" style="document"/>
      <input>
        <soap:body use="literal"/>
      </input>
      <output>
        <soap:body use="literal"/>
      </output>
    </operation>
  </binding>
  <binding name="CountryInfoServiceSoapBinding12" type="tns:CountryInfoServiceSoapType">
    <soap12:binding style="document" transport="http://schemas.xmlsoap.org/soap/http"/>
    <operation name="ListOfContinentsByName">
      <soap12:operation soapAction="" style="document"/>
      <input>
        <soap12:body use="literal"/>
      </input>
      <output>
        <soap12:body use="literal"/>
      </output>
    </operation>
    <operation name="ListOfContinentsByCode">
      <soap12:operation soapAction="" style="document"/>
      <input>
        <soap12:body use="literal"/>
      </input>
      <output>
        <soap12:body use="literal"/>
      </output>
    </operation>
    <operation name="ListOfCurrenciesByName">
      <soap12:operation soapAction="" style="document"/>
      <input>
        <soap12:body use="literal"/>
      </input>
      <output>
        <soap12:body use="literal"/>
      </output>
    </operation>
    <operation name="ListOfCurrenciesByCode">
      <soap12:operation soapAction="" style="document"/>
      <input>
        <soap12:body use="literal"/>
      </input>
      <output>
        <soap12:body use="literal"/>
      </output>
    </operation>
    <operation name="CurrencyName">
      <soap12:operation soapAction="" style="document"/>
      <input>
        <soap12:body use="literal"/>
      </input>
      <output>
        <soap12:body use="literal"/>
      </output>
    </operation>
    <operation name="ListOfCountryNamesByCode">
      <soap12:operation soapAction="" style="document"/>
      <input>
        <soap12:body use="literal"/>
      </input>
      <output>
        <soap12:body use="literal"/>
      </output>
    </operation>
    <operation name="ListOfCountryNamesByName">
      <soap12:operation soapAction="" style="document"/>
      <input>
        <soap12:body use="literal"/>
      </input>
      <output>
        <soap12:body use="literal"/>
      </output>
    </operation>
    <operation name="ListOfCountryNamesGroupedByContinent">
      <soap12:operation soapAction="" style="document"/>
      <input>
        <soap12:body use="literal"/>
      </input>
      <output>
        <soap12:body use="literal"/>
      </output>
    </operation>
    <operation name="CountryName">
      <soap12:operation soapAction="" style="document"/>
      <input>
        <soap12:body use="literal"/>
      </input>
      <output>
        <soap12:body use="literal"/>
      </output>
    </operation>
    <operation name="CountryISOCode">
      <soap12:operation soapAction="" style="document"/>
      <input>
        <soap12:body use="literal"/>
      </input>
      <output>
        <soap12:body use="literal"/>
      </output>
    </operation>
    <operation name="CapitalCity">
      <soap12:operation soapAction="" style="document"/>
      <input>
        <soap12:body use="literal"/>
      </input>
      <output>
        <soap12:body use="literal"/>
      </output>
    </operation>
    <operation name="CountryCurrency">
      <soap12:operation soapAction="" style="document"/>
      <input>
        <soap12:body use="literal"/>
      </input>
      <output>
        <soap12:body use="literal"/>
      </output>
    </operation>
    <operation name="CountryFlag">
      <soap12:operation soapAction="" style="document"/>
      <input>
        <soap12:body use="literal"/>
      </input>
      <output>
        <soap12:body use="literal"/>
      </output>
    </operation>
    <operation name="CountryIntPhoneCode">
      <soap12:operation soapAction="" style="document"/>
      <input>
        <soap12:body use="literal"/>
      </input>
      <output>
        <soap12:body use="literal"/>
      </output>
    </operation>
    <operation name="FullCountryInfo">
      <soap12:operation soapAction="" style="document"/>
      <input>
        <soap12:body use="literal"/>
      </input>
      <output>
        <soap12:body use="literal"/>
      </output>
    </operation>
    <operation name="FullCountryInfoAllCountries">
      <soap12:operation soapAction="" style="document"/>
      <input>
        <soap12:body use="literal"/>
      </input>
      <output>
        <soap12:body use="literal"/>
      </output>
    </operation>
    <operation name="CountriesUsingCurrency">
      <soap12:operation soapAction="" style="document"/>
      <input>
        <soap12:body use="literal"/>
      </input>
      <output>
        <soap12:body use="literal"/>
      </output>
    </operation>
    <operation name="ListOfLanguagesByName">
      <soap12:operation soapAction="" style="document"/>
      <input>
        <soap12:body use="literal"/>
      </input>
      <output>
        <soap12:body use="literal"/>
      </output>
    </operation>
    <operation name="ListOfLanguagesByCode">
      <soap12:operation soapAction="" style="document"/>
      <input>
        <soap12:body use="literal"/>
      </input>
      <output>
        <soap12:body use="literal"/>
      </output>
    </operation>
    <operation name="LanguageName">
      <soap12:operation soapAction="" style="document"/>
      <input>
        <soap12:body use="literal"/>
      </input>
      <output>
        <soap12:body use="literal"/>
      </output>
    </operation>
    <operation name="LanguageISOCode">
      <soap12:operation soapAction="" style="document"/>
      <input>
        <soap12:body use="literal"/>
      </input>
      <output>
        <soap12:body use="literal"/>
      </output>
    </operation>
  </binding>
  <service name="CountryInfoService">
    <documentation>This DataFlex Web Service opens up country information. 2 letter ISO codes are used for Country code. There are functions to retrieve the used Currency, Language, Capital City, Continent and Telephone code.</documentation>
    <port name="CountryInfoServiceSoap" binding="tns:CountryInfoServiceSoapBinding">
      <soap:address location="http://www.oorsprong.org/websamples.countryinfo/CountryInfoService.wso"/>
    </port>
    <port name="CountryInfoServiceSoap12" binding="tns:CountryInfoServiceSoapBinding12">
      <soap12:address location="http://www.oorsprong.org/websamples.countryinfo/CountryInfoService.wso"/>
    </port>
  </service>
</definitions>]]></con:content><con:type>http://schemas.xmlsoap.org/wsdl/</con:type></con:part></con:definitionCache><con:endpoints><con:endpoint>http://www.oorsprong.org/websamples.countryinfo/CountryInfoService.wso</con:endpoint></con:endpoints><con:operation id="cdfcce1b-43aa-4bdf-b456-41fca4c62f4e" isOneWay="false" action="" name="CapitalCity" bindingOperationName="CapitalCity" type="Request-Response" inputName="" receivesAttachments="false" sendsAttachments="false" anonymous="optional"><con:settings/><con:call id="8caadce7-e0f5-4125-aa48-b579544b5aaa" name="Request 1"><con:settings><con:setting id="com.eviware.soapui.impl.wsdl.WsdlRequest@request-headers">&lt;xml-fragment/></con:setting></con:settings><con:encoding>UTF-8</con:encoding><con:endpoint>http://www.oorsprong.org/websamples.countryinfo/CountryInfoService.wso</con:endpoint><con:request><![CDATA[<soapenv:Envelope xmlns:soapenv="http://schemas.xmlsoap.org/soap/envelope/" xmlns:web="http://www.oorsprong.org/websamples.countryinfo">
   <soapenv:Header/>
   <soapenv:Body>
      <web:CapitalCity>
         <web:sCountryISOCode>CN</web:sCountryISOCode>
      </web:CapitalCity>
   </soapenv:Body>
</soapenv:Envelope>]]></con:request><con:credentials><con:authType>No Authorization</con:authType></con:credentials><con:jmsConfig JMSDeliveryMode="PERSISTENT"/><con:jmsPropertyConfig/><con:wsaConfig mustUnderstand="NONE" version="200508" action="http://www.oorsprong.org/websamples.countryinfo/CountryInfoServiceSoapType/CapitalCityRequest"/><con:wsrmConfig version="1.2"/></con:call></con:operation><con:operation id="eddb2bb1-d206-440f-817d-83d0d5189ffe" isOneWay="false" action="" name="CountriesUsingCurrency" bindingOperationName="CountriesUsingCurrency" type="Request-Response" inputName="" receivesAttachments="false" sendsAttachments="false" anonymous="optional"><con:settings/><con:call id="fc9ee6a1-f3f4-4551-a335-c75d11b8c7ae" name="Request 1"><con:settings/><con:encoding>UTF-8</con:encoding><con:endpoint>http://www.oorsprong.org/websamples.countryinfo/CountryInfoService.wso</con:endpoint><con:request><![CDATA[<soapenv:Envelope xmlns:soapenv="http://schemas.xmlsoap.org/soap/envelope/" xmlns:web="http://www.oorsprong.org/websamples.countryinfo">
   <soapenv:Header/>
   <soapenv:Body>
      <web:CountriesUsingCurrency>
         <web:sISOCurrencyCode>?</web:sISOCurrencyCode>
      </web:CountriesUsingCurrency>
   </soapenv:Body>
</soapenv:Envelope>]]></con:request><con:wsaConfig mustUnderstand="NONE" version="200508" action="http://www.oorsprong.org/websamples.countryinfo/CountryInfoServiceSoapType/CountriesUsingCurrencyRequest"/></con:call></con:operation><con:operation id="85c2ed62-4f63-41a9-b8ff-7c45b64a27ec" isOneWay="false" action="" name="CountryCurrency" bindingOperationName="CountryCurrency" type="Request-Response" inputName="" receivesAttachments="false" sendsAttachments="false" anonymous="optional"><con:settings/><con:call id="c11199f0-a292-4b72-b599-fa95a313c630" name="Request 1"><con:settings/><con:encoding>UTF-8</con:encoding><con:endpoint>http://www.oorsprong.org/websamples.countryinfo/CountryInfoService.wso</con:endpoint><con:request><![CDATA[<soapenv:Envelope xmlns:soapenv="http://schemas.xmlsoap.org/soap/envelope/" xmlns:web="http://www.oorsprong.org/websamples.countryinfo">
   <soapenv:Header/>
   <soapenv:Body>
      <web:CountryCurrency>
         <web:sCountryISOCode>?</web:sCountryISOCode>
      </web:CountryCurrency>
   </soapenv:Body>
</soapenv:Envelope>]]></con:request><con:wsaConfig mustUnderstand="NONE" version="200508" action="http://www.oorsprong.org/websamples.countryinfo/CountryInfoServiceSoapType/CountryCurrencyRequest"/></con:call></con:operation><con:operation id="2ab57d09-06c5-437e-a48f-1df5c59dfd91" isOneWay="false" action="" name="CountryFlag" bindingOperationName="CountryFlag" type="Request-Response" inputName="" receivesAttachments="false" sendsAttachments="false" anonymous="optional"><con:settings/><con:call id="20667357-e822-4fa3-b2c3-d65264036642" name="Request 1"><con:settings/><con:encoding>UTF-8</con:encoding><con:endpoint>http://www.oorsprong.org/websamples.countryinfo/CountryInfoService.wso</con:endpoint><con:request><![CDATA[<soapenv:Envelope xmlns:soapenv="http://schemas.xmlsoap.org/soap/envelope/" xmlns:web="http://www.oorsprong.org/websamples.countryinfo">
   <soapenv:Header/>
   <soapenv:Body>
      <web:CountryFlag>
         <web:sCountryISOCode>?</web:sCountryISOCode>
      </web:CountryFlag>
   </soapenv:Body>
</soapenv:Envelope>]]></con:request><con:wsaConfig mustUnderstand="NONE" version="200508" action="http://www.oorsprong.org/websamples.countryinfo/CountryInfoServiceSoapType/CountryFlagRequest"/></con:call></con:operation><con:operation id="ce22b019-b4b0-4070-a6e6-133e0e9804a0" isOneWay="false" action="" name="CountryIntPhoneCode" bindingOperationName="CountryIntPhoneCode" type="Request-Response" inputName="" receivesAttachments="false" sendsAttachments="false" anonymous="optional"><con:settings/><con:call id="2d6f0f11-08d3-4c24-9f79-9ed5797e02b8" name="Request 1"><con:settings/><con:encoding>UTF-8</con:encoding><con:endpoint>http://www.oorsprong.org/websamples.countryinfo/CountryInfoService.wso</con:endpoint><con:request><![CDATA[<soapenv:Envelope xmlns:soapenv="http://schemas.xmlsoap.org/soap/envelope/" xmlns:web="http://www.oorsprong.org/websamples.countryinfo">
   <soapenv:Header/>
   <soapenv:Body>
      <web:CountryIntPhoneCode>
         <web:sCountryISOCode>?</web:sCountryISOCode>
      </web:CountryIntPhoneCode>
   </soapenv:Body>
</soapenv:Envelope>]]></con:request><con:wsaConfig mustUnderstand="NONE" version="200508" action="http://www.oorsprong.org/websamples.countryinfo/CountryInfoServiceSoapType/CountryIntPhoneCodeRequest"/></con:call></con:operation><con:operation id="f34ec482-e922-4c9e-95c9-7152683c5bf8" isOneWay="false" action="" name="CountryISOCode" bindingOperationName="CountryISOCode" type="Request-Response" inputName="" receivesAttachments="false" sendsAttachments="false" anonymous="optional"><con:settings/><con:call id="74b646a7-09ab-4c22-9cef-ccfc35db5c23" name="Request 1"><con:settings/><con:encoding>UTF-8</con:encoding><con:endpoint>http://www.oorsprong.org/websamples.countryinfo/CountryInfoService.wso</con:endpoint><con:request><![CDATA[<soapenv:Envelope xmlns:soapenv="http://schemas.xmlsoap.org/soap/envelope/" xmlns:web="http://www.oorsprong.org/websamples.countryinfo">
   <soapenv:Header/>
   <soapenv:Body>
      <web:CountryISOCode>
         <web:sCountryName>?</web:sCountryName>
      </web:CountryISOCode>
   </soapenv:Body>
</soapenv:Envelope>]]></con:request><con:wsaConfig mustUnderstand="NONE" version="200508" action="http://www.oorsprong.org/websamples.countryinfo/CountryInfoServiceSoapType/CountryISOCodeRequest"/></con:call></con:operation><con:operation id="d2c1c021-d2f6-45ba-842c-956048ef63f7" isOneWay="false" action="" name="CountryName" bindingOperationName="CountryName" type="Request-Response" inputName="" receivesAttachments="false" sendsAttachments="false" anonymous="optional"><con:settings/><con:call id="7d56a7f9-8a59-4d57-87d0-f5fff10842fb" name="Request 1"><con:settings/><con:encoding>UTF-8</con:encoding><con:endpoint>http://www.oorsprong.org/websamples.countryinfo/CountryInfoService.wso</con:endpoint><con:request><![CDATA[<soapenv:Envelope xmlns:soapenv="http://schemas.xmlsoap.org/soap/envelope/" xmlns:web="http://www.oorsprong.org/websamples.countryinfo">
   <soapenv:Header/>
   <soapenv:Body>
      <web:CountryName>
         <web:sCountryISOCode>?</web:sCountryISOCode>
      </web:CountryName>
   </soapenv:Body>
</soapenv:Envelope>]]></con:request><con:wsaConfig mustUnderstand="NONE" version="200508" action="http://www.oorsprong.org/websamples.countryinfo/CountryInfoServiceSoapType/CountryNameRequest"/></con:call></con:operation><con:operation id="55abbb2c-31d7-458a-acf6-8e568129bf21" isOneWay="false" action="" name="CurrencyName" bindingOperationName="CurrencyName" type="Request-Response" inputName="" receivesAttachments="false" sendsAttachments="false" anonymous="optional"><con:settings/><con:call id="c8078b65-b6c7-4d23-9192-4644cef77079" name="Request 1"><con:settings/><con:encoding>UTF-8</con:encoding><con:endpoint>http://www.oorsprong.org/websamples.countryinfo/CountryInfoService.wso</con:endpoint><con:request><![CDATA[<soapenv:Envelope xmlns:soapenv="http://schemas.xmlsoap.org/soap/envelope/" xmlns:web="http://www.oorsprong.org/websamples.countryinfo">
   <soapenv:Header/>
   <soapenv:Body>
      <web:CurrencyName>
         <web:sCurrencyISOCode>?</web:sCurrencyISOCode>
      </web:CurrencyName>
   </soapenv:Body>
</soapenv:Envelope>]]></con:request><con:wsaConfig mustUnderstand="NONE" version="200508" action="http://www.oorsprong.org/websamples.countryinfo/CountryInfoServiceSoapType/CurrencyNameRequest"/></con:call></con:operation><con:operation id="db0fb229-8c76-4c6d-afe5-486224f2f0bd" isOneWay="false" action="" name="FullCountryInfo" bindingOperationName="FullCountryInfo" type="Request-Response" inputName="" receivesAttachments="false" sendsAttachments="false" anonymous="optional"><con:settings/><con:call id="08776b82-6134-462e-a196-51de5cd5272b" name="Request 1"><con:settings/><con:encoding>UTF-8</con:encoding><con:endpoint>http://www.oorsprong.org/websamples.countryinfo/CountryInfoService.wso</con:endpoint><con:request><![CDATA[<soapenv:Envelope xmlns:soapenv="http://schemas.xmlsoap.org/soap/envelope/" xmlns:web="http://www.oorsprong.org/websamples.countryinfo">
   <soapenv:Header/>
   <soapenv:Body>
      <web:FullCountryInfo>
         <web:sCountryISOCode>?</web:sCountryISOCode>
      </web:FullCountryInfo>
   </soapenv:Body>
</soapenv:Envelope>]]></con:request><con:wsaConfig mustUnderstand="NONE" version="200508" action="http://www.oorsprong.org/websamples.countryinfo/CountryInfoServiceSoapType/FullCountryInfoRequest"/></con:call></con:operation><con:operation id="e93deb8b-29c8-4501-a282-7c8a1858ae4a" isOneWay="false" action="" name="FullCountryInfoAllCountries" bindingOperationName="FullCountryInfoAllCountries" type="Request-Response" inputName="" receivesAttachments="false" sendsAttachments="false" anonymous="optional"><con:settings/><con:call id="4c7fc928-d00d-4131-b3ed-7b5259790695" name="Request 1"><con:settings/><con:encoding>UTF-8</con:encoding><con:endpoint>http://www.oorsprong.org/websamples.countryinfo/CountryInfoService.wso</con:endpoint><con:request><![CDATA[<soapenv:Envelope xmlns:soapenv="http://schemas.xmlsoap.org/soap/envelope/" xmlns:web="http://www.oorsprong.org/websamples.countryinfo">
   <soapenv:Header/>
   <soapenv:Body>
      <web:FullCountryInfoAllCountries/>
   </soapenv:Body>
</soapenv:Envelope>]]></con:request><con:wsaConfig mustUnderstand="NONE" version="200508" action="http://www.oorsprong.org/websamples.countryinfo/CountryInfoServiceSoapType/FullCountryInfoAllCountriesRequest"/></con:call></con:operation><con:operation id="aa63cb67-5c37-4624-bf2c-4a676ee8d699" isOneWay="false" action="" name="LanguageISOCode" bindingOperationName="LanguageISOCode" type="Request-Response" inputName="" receivesAttachments="false" sendsAttachments="false" anonymous="optional"><con:settings/><con:call id="f36fe180-69c8-4635-bd85-855453afad3e" name="Request 1"><con:settings/><con:encoding>UTF-8</con:encoding><con:endpoint>http://www.oorsprong.org/websamples.countryinfo/CountryInfoService.wso</con:endpoint><con:request><![CDATA[<soapenv:Envelope xmlns:soapenv="http://schemas.xmlsoap.org/soap/envelope/" xmlns:web="http://www.oorsprong.org/websamples.countryinfo">
   <soapenv:Header/>
   <soapenv:Body>
      <web:LanguageISOCode>
         <web:sLanguageName>?</web:sLanguageName>
      </web:LanguageISOCode>
   </soapenv:Body>
</soapenv:Envelope>]]></con:request><con:wsaConfig mustUnderstand="NONE" version="200508" action="http://www.oorsprong.org/websamples.countryinfo/CountryInfoServiceSoapType/LanguageISOCodeRequest"/></con:call></con:operation><con:operation id="6ff155cc-7a4c-45bf-9613-6851f6e3d77f" isOneWay="false" action="" name="LanguageName" bindingOperationName="LanguageName" type="Request-Response" inputName="" receivesAttachments="false" sendsAttachments="false" anonymous="optional"><con:settings/><con:call id="d78b8e71-b0ca-4297-9f97-717bd59b03a4" name="Request 1"><con:settings/><con:encoding>UTF-8</con:encoding><con:endpoint>http://www.oorsprong.org/websamples.countryinfo/CountryInfoService.wso</con:endpoint><con:request><![CDATA[<soapenv:Envelope xmlns:soapenv="http://schemas.xmlsoap.org/soap/envelope/" xmlns:web="http://www.oorsprong.org/websamples.countryinfo">
   <soapenv:Header/>
   <soapenv:Body>
      <web:LanguageName>
         <web:sISOCode>?</web:sISOCode>
      </web:LanguageName>
   </soapenv:Body>
</soapenv:Envelope>]]></con:request><con:wsaConfig mustUnderstand="NONE" version="200508" action="http://www.oorsprong.org/websamples.countryinfo/CountryInfoServiceSoapType/LanguageNameRequest"/></con:call></con:operation><con:operation id="6cee64ca-4007-49d4-9239-600c07be06c7" isOneWay="false" action="" name="ListOfContinentsByCode" bindingOperationName="ListOfContinentsByCode" type="Request-Response" inputName="" receivesAttachments="false" sendsAttachments="false" anonymous="optional"><con:settings/><con:call id="baf9da71-6e09-46cf-b86a-d4e60d15c3b7" name="Request 1"><con:settings/><con:encoding>UTF-8</con:encoding><con:endpoint>http://www.oorsprong.org/websamples.countryinfo/CountryInfoService.wso</con:endpoint><con:request><![CDATA[<soapenv:Envelope xmlns:soapenv="http://schemas.xmlsoap.org/soap/envelope/" xmlns:web="http://www.oorsprong.org/websamples.countryinfo">
   <soapenv:Header/>
   <soapenv:Body>
      <web:ListOfContinentsByCode/>
   </soapenv:Body>
</soapenv:Envelope>]]></con:request><con:wsaConfig mustUnderstand="NONE" version="200508" action="http://www.oorsprong.org/websamples.countryinfo/CountryInfoServiceSoapType/ListOfContinentsByCodeRequest"/></con:call></con:operation><con:operation id="81f1206d-afa3-4464-9623-1890cc3e897e" isOneWay="false" action="" name="ListOfContinentsByName" bindingOperationName="ListOfContinentsByName" type="Request-Response" inputName="" receivesAttachments="false" sendsAttachments="false" anonymous="optional"><con:settings/><con:call id="91c9ce6e-0066-4781-a72e-0faceda85542" name="Request 1"><con:settings/><con:encoding>UTF-8</con:encoding><con:endpoint>http://www.oorsprong.org/websamples.countryinfo/CountryInfoService.wso</con:endpoint><con:request><![CDATA[<soapenv:Envelope xmlns:soapenv="http://schemas.xmlsoap.org/soap/envelope/" xmlns:web="http://www.oorsprong.org/websamples.countryinfo">
   <soapenv:Header/>
   <soapenv:Body>
      <web:ListOfContinentsByName/>
   </soapenv:Body>
</soapenv:Envelope>]]></con:request><con:wsaConfig mustUnderstand="NONE" version="200508" action="http://www.oorsprong.org/websamples.countryinfo/CountryInfoServiceSoapType/ListOfContinentsByNameRequest"/></con:call></con:operation><con:operation id="e7e52713-aac3-4222-a6ab-aeb60f1ebafb" isOneWay="false" action="" name="ListOfCountryNamesByCode" bindingOperationName="ListOfCountryNamesByCode" type="Request-Response" inputName="" receivesAttachments="false" sendsAttachments="false" anonymous="optional"><con:settings/><con:call id="6eb6e6b6-d5a1-467c-8c62-9b856edfe109" name="Request 1"><con:settings/><con:encoding>UTF-8</con:encoding><con:endpoint>http://www.oorsprong.org/websamples.countryinfo/CountryInfoService.wso</con:endpoint><con:request><![CDATA[<soapenv:Envelope xmlns:soapenv="http://schemas.xmlsoap.org/soap/envelope/" xmlns:web="http://www.oorsprong.org/websamples.countryinfo">
   <soapenv:Header/>
   <soapenv:Body>
      <web:ListOfCountryNamesByCode/>
   </soapenv:Body>
</soapenv:Envelope>]]></con:request><con:wsaConfig mustUnderstand="NONE" version="200508" action="http://www.oorsprong.org/websamples.countryinfo/CountryInfoServiceSoapType/ListOfCountryNamesByCodeRequest"/></con:call></con:operation><con:operation id="2739da01-da43-4002-bcc5-3d8bb581f32e" isOneWay="false" action="" name="ListOfCountryNamesByName" bindingOperationName="ListOfCountryNamesByName" type="Request-Response" inputName="" receivesAttachments="false" sendsAttachments="false" anonymous="optional"><con:settings/><con:call id="eb968ab4-545d-4f81-809c-87ac204c1ee9" name="Request 1"><con:settings/><con:encoding>UTF-8</con:encoding><con:endpoint>http://www.oorsprong.org/websamples.countryinfo/CountryInfoService.wso</con:endpoint><con:request><![CDATA[<soapenv:Envelope xmlns:soapenv="http://schemas.xmlsoap.org/soap/envelope/" xmlns:web="http://www.oorsprong.org/websamples.countryinfo">
   <soapenv:Header/>
   <soapenv:Body>
      <web:ListOfCountryNamesByName/>
   </soapenv:Body>
</soapenv:Envelope>]]></con:request><con:wsaConfig mustUnderstand="NONE" version="200508" action="http://www.oorsprong.org/websamples.countryinfo/CountryInfoServiceSoapType/ListOfCountryNamesByNameRequest"/></con:call></con:operation><con:operation id="1e0f858c-8872-454e-bae0-038735db4f39" isOneWay="false" action="" name="ListOfCountryNamesGroupedByContinent" bindingOperationName="ListOfCountryNamesGroupedByContinent" type="Request-Response" inputName="" receivesAttachments="false" sendsAttachments="false" anonymous="optional"><con:settings/><con:call id="a1d19fe9-52ee-4c17-9fe5-2b6f4e16d305" name="Request 1"><con:settings/><con:encoding>UTF-8</con:encoding><con:endpoint>http://www.oorsprong.org/websamples.countryinfo/CountryInfoService.wso</con:endpoint><con:request><![CDATA[<soapenv:Envelope xmlns:soapenv="http://schemas.xmlsoap.org/soap/envelope/" xmlns:web="http://www.oorsprong.org/websamples.countryinfo">
   <soapenv:Header/>
   <soapenv:Body>
      <web:ListOfCountryNamesGroupedByContinent/>
   </soapenv:Body>
</soapenv:Envelope>]]></con:request><con:wsaConfig mustUnderstand="NONE" version="200508" action="http://www.oorsprong.org/websamples.countryinfo/CountryInfoServiceSoapType/ListOfCountryNamesGroupedByContinentRequest"/></con:call></con:operation><con:operation id="34cf8db1-4e5e-495b-b6bd-307b98a0889c" isOneWay="false" action="" name="ListOfCurrenciesByCode" bindingOperationName="ListOfCurrenciesByCode" type="Request-Response" inputName="" receivesAttachments="false" sendsAttachments="false" anonymous="optional"><con:settings/><con:call id="b1ade702-4ad3-43c7-815f-267ffd7d7d59" name="Request 1"><con:settings/><con:encoding>UTF-8</con:encoding><con:endpoint>http://www.oorsprong.org/websamples.countryinfo/CountryInfoService.wso</con:endpoint><con:request><![CDATA[<soapenv:Envelope xmlns:soapenv="http://schemas.xmlsoap.org/soap/envelope/" xmlns:web="http://www.oorsprong.org/websamples.countryinfo">
   <soapenv:Header/>
   <soapenv:Body>
      <web:ListOfCurrenciesByCode/>
   </soapenv:Body>
</soapenv:Envelope>]]></con:request><con:wsaConfig mustUnderstand="NONE" version="200508" action="http://www.oorsprong.org/websamples.countryinfo/CountryInfoServiceSoapType/ListOfCurrenciesByCodeRequest"/></con:call></con:operation><con:operation id="861f4765-e2c5-4d48-a19d-4cfdbb6d0bb9" isOneWay="false" action="" name="ListOfCurrenciesByName" bindingOperationName="ListOfCurrenciesByName" type="Request-Response" inputName="" receivesAttachments="false" sendsAttachments="false" anonymous="optional"><con:settings/><con:call id="f132abc8-6fd5-4688-9dea-312177f8af07" name="Request 1"><con:settings/><con:encoding>UTF-8</con:encoding><con:endpoint>http://www.oorsprong.org/websamples.countryinfo/CountryInfoService.wso</con:endpoint><con:request><![CDATA[<soapenv:Envelope xmlns:soapenv="http://schemas.xmlsoap.org/soap/envelope/" xmlns:web="http://www.oorsprong.org/websamples.countryinfo">
   <soapenv:Header/>
   <soapenv:Body>
      <web:ListOfCurrenciesByName/>
   </soapenv:Body>
</soapenv:Envelope>]]></con:request><con:wsaConfig mustUnderstand="NONE" version="200508" action="http://www.oorsprong.org/websamples.countryinfo/CountryInfoServiceSoapType/ListOfCurrenciesByNameRequest"/></con:call></con:operation><con:operation id="f4e588d5-87b4-4e5f-bd67-5cf6f04e2c4c" isOneWay="false" action="" name="ListOfLanguagesByCode" bindingOperationName="ListOfLanguagesByCode" type="Request-Response" inputName="" receivesAttachments="false" sendsAttachments="false" anonymous="optional"><con:settings/><con:call id="c623e918-491d-4300-ae0f-13c272be3994" name="Request 1"><con:settings/><con:encoding>UTF-8</con:encoding><con:endpoint>http://www.oorsprong.org/websamples.countryinfo/CountryInfoService.wso</con:endpoint><con:request><![CDATA[<soapenv:Envelope xmlns:soapenv="http://schemas.xmlsoap.org/soap/envelope/" xmlns:web="http://www.oorsprong.org/websamples.countryinfo">
   <soapenv:Header/>
   <soapenv:Body>
      <web:ListOfLanguagesByCode/>
   </soapenv:Body>
</soapenv:Envelope>]]></con:request><con:wsaConfig mustUnderstand="NONE" version="200508" action="http://www.oorsprong.org/websamples.countryinfo/CountryInfoServiceSoapType/ListOfLanguagesByCodeRequest"/></con:call></con:operation><con:operation id="43e3af54-0d49-4c4c-983d-dd27e1a7ceea" isOneWay="false" action="" name="ListOfLanguagesByName" bindingOperationName="ListOfLanguagesByName" type="Request-Response" inputName="" receivesAttachments="false" sendsAttachments="false" anonymous="optional"><con:settings/><con:call id="97853dcf-10db-4898-97d4-41266813a6e0" name="Request 1"><con:settings/><con:encoding>UTF-8</con:encoding><con:endpoint>http://www.oorsprong.org/websamples.countryinfo/CountryInfoService.wso</con:endpoint><con:request><![CDATA[<soapenv:Envelope xmlns:soapenv="http://schemas.xmlsoap.org/soap/envelope/" xmlns:web="http://www.oorsprong.org/websamples.countryinfo">
   <soapenv:Header/>
   <soapenv:Body>
      <web:ListOfLanguagesByName/>
   </soapenv:Body>
</soapenv:Envelope>]]></con:request><con:wsaConfig mustUnderstand="NONE" version="200508" action="http://www.oorsprong.org/websamples.countryinfo/CountryInfoServiceSoapType/ListOfLanguagesByNameRequest"/></con:call></con:operation></con:interface><con:testSuite id="dfc801c0-819d-42b2-a55a-4211b483bcca" name="TEST SUITE 1"><con:settings/><con:runType>PARALLELL</con:runType><con:testCase id="c224e373-4419-4663-bf4f-07a9c231cc4d" failOnError="true" failTestCaseOnErrors="true" keepSession="false" maxResults="0" name="CapitalCity TestCase" searchProperties="true"><con:settings/><con:testStep type="request" id="7a7479b7-6786-4459-9cc7-8cd01c642fd2" name="CapitalCity"><con:settings/><con:config xsi:type="con:RequestStep" xmlns:xsi="http://www.w3.org/2001/XMLSchema-instance"><con:interface>CountryInfoServiceSoapBinding</con:interface><con:operation>CapitalCity</con:operation><con:request name="CapitalCity" id="4a50a2cb-2ebe-459a-b62d-7338e9e62f35"><con:settings><con:setting id="com.eviware.soapui.impl.wsdl.WsdlRequest@request-headers">&lt;xml-fragment/></con:setting></con:settings><con:encoding>UTF-8</con:encoding><con:endpoint>http://www.oorsprong.org/websamples.countryinfo/CountryInfoService.wso</con:endpoint><con:request><![CDATA[<soapenv:Envelope xmlns:soapenv="http://schemas.xmlsoap.org/soap/envelope/" xmlns:web="http://www.oorsprong.org/websamples.countryinfo">
   <soapenv:Header/>
   <soapenv:Body>
      <web:CapitalCity>
         <web:sCountryISOCode>US</web:sCountryISOCode>
      </web:CapitalCity>
   </soapenv:Body>
</soapenv:Envelope>]]></con:request><con:assertion type="Simple Contains" id="1a341184-ec4f-44e8-b94a-19fd1fd87516" name="Contains"><con:configuration><token>Washington</token><ignoreCase>false</ignoreCase><useRegEx>false</useRegEx></con:configuration></con:assertion><con:credentials><con:authType>No Authorization</con:authType></con:credentials><con:jmsConfig JMSDeliveryMode="PERSISTENT"/><con:jmsPropertyConfig/><con:wsaConfig action="http://www.oorsprong.org/websamples.countryinfo/CountryInfoServiceSoapType/CapitalCityRequest" mustUnderstand="NONE" version="200508"/><con:wsrmConfig version="1.2"/></con:request></con:config></con:testStep><con:testStep type="groovy" name="Groovy Script" id="6d267c6c-bbc4-4cf6-9496-6536ac132a4d"><con:settings/><con:config><script/></con:config></con:testStep><con:properties/></con:testCase><con:testCase id="73974b28-2bd9-44e3-8dbe-ec62e8ab8a81" failOnError="true" failTestCaseOnErrors="true" keepSession="false" maxResults="0" name="CountriesUsingCurrency TestCase" searchProperties="true"><con:settings/><con:testStep type="request" id="2f6bc4e6-1557-4718-a57f-2944dfc5643b" name="CountriesUsingCurrency"><con:settings/><con:config xsi:type="con:RequestStep" xmlns:xsi="http://www.w3.org/2001/XMLSchema-instance"><con:interface>CountryInfoServiceSoapBinding</con:interface><con:operation>CountriesUsingCurrency</con:operation><con:request name="CountriesUsingCurrency" id="9fdb952b-2099-426f-99e6-02c304b9ce66"><con:settings><con:setting id="com.eviware.soapui.impl.wsdl.WsdlRequest@request-headers">&lt;xml-fragment/></con:setting></con:settings><con:encoding>UTF-8</con:encoding><con:endpoint>http://www.oorsprong.org/websamples.countryinfo/CountryInfoService.wso</con:endpoint><con:request><![CDATA[<soapenv:Envelope xmlns:soapenv="http://schemas.xmlsoap.org/soap/envelope/" xmlns:web="http://www.oorsprong.org/websamples.countryinfo">
   <soapenv:Header/>
   <soapenv:Body>
      <web:CountriesUsingCurrency>
         <web:sISOCurrencyCode>CNY</web:sISOCurrencyCode>
      </web:CountriesUsingCurrency>
   </soapenv:Body>
</soapenv:Envelope>]]></con:request><con:assertion type="Simple Contains" id="39edcaa8-0ecb-46b0-9356-9e9758897fe3" name="Contains"><con:configuration><token>CN</token><ignoreCase>false</ignoreCase><useRegEx>false</useRegEx></con:configuration></con:assertion><con:credentials><con:authType>No Authorization</con:authType></con:credentials><con:jmsConfig JMSDeliveryMode="PERSISTENT"/><con:jmsPropertyConfig/><con:wsaConfig action="http://www.oorsprong.org/websamples.countryinfo/CountryInfoServiceSoapType/CountriesUsingCurrencyRequest" mustUnderstand="NONE" version="200508"/><con:wsrmConfig version="1.2"/></con:request></con:config></con:testStep><con:properties/></con:testCase><con:testCase id="53c8b1c0-f96a-4a0f-af3f-17f7acef0d20" failOnError="true" failTestCaseOnErrors="true" keepSession="false" maxResults="0" name="CountryCurrency TestCase" searchProperties="true"><con:settings/><con:testStep type="request" id="f4f0fb22-b830-4910-afc3-f2b5dced0ddf" name="CountryCurrency"><con:settings/><con:config xsi:type="con:RequestStep" xmlns:xsi="http://www.w3.org/2001/XMLSchema-instance"><con:interface>CountryInfoServiceSoapBinding</con:interface><con:operation>CountryCurrency</con:operation><con:request name="CountryCurrency" id="5164e1a9-dae3-4f95-89bd-0c8bead8c770"><con:settings/><con:encoding>UTF-8</con:encoding><con:endpoint>http://www.oorsprong.org/websamples.countryinfo/CountryInfoService.wso</con:endpoint><con:request><![CDATA[<soapenv:Envelope xmlns:soapenv="http://schemas.xmlsoap.org/soap/envelope/" xmlns:web="http://www.oorsprong.org/websamples.countryinfo">
   <soapenv:Header/>
   <soapenv:Body>
      <web:CountryCurrency>
         <web:sCountryISOCode>?</web:sCountryISOCode>
      </web:CountryCurrency>
   </soapenv:Body>
</soapenv:Envelope>]]></con:request><con:credentials><con:authType>No Authorization</con:authType></con:credentials><con:wsaConfig action="http://www.oorsprong.org/websamples.countryinfo/CountryInfoServiceSoapType/CountryCurrencyRequest"/></con:request></con:config></con:testStep><con:properties/></con:testCase><con:testCase id="d4696328-2ec2-4d66-9d3e-2ba331b0c7c7" failOnError="true" failTestCaseOnErrors="true" keepSession="false" maxResults="0" name="CountryFlag TestCase" searchProperties="true"><con:settings/><con:testStep type="request" id="d1554e5d-108f-4cab-af9f-65fa95cf46a8" name="CountryFlag"><con:settings/><con:config xsi:type="con:RequestStep" xmlns:xsi="http://www.w3.org/2001/XMLSchema-instance"><con:interface>CountryInfoServiceSoapBinding</con:interface><con:operation>CountryFlag</con:operation><con:request name="CountryFlag" id="5aaa819f-3660-4d29-972a-8dc0f054b0ac"><con:settings/><con:encoding>UTF-8</con:encoding><con:endpoint>http://www.oorsprong.org/websamples.countryinfo/CountryInfoService.wso</con:endpoint><con:request><![CDATA[<soapenv:Envelope xmlns:soapenv="http://schemas.xmlsoap.org/soap/envelope/" xmlns:web="http://www.oorsprong.org/websamples.countryinfo">
   <soapenv:Header/>
   <soapenv:Body>
      <web:CountryFlag>
         <web:sCountryISOCode>?</web:sCountryISOCode>
      </web:CountryFlag>
   </soapenv:Body>
</soapenv:Envelope>]]></con:request><con:credentials><con:authType>No Authorization</con:authType></con:credentials><con:wsaConfig action="http://www.oorsprong.org/websamples.countryinfo/CountryInfoServiceSoapType/CountryFlagRequest"/></con:request></con:config></con:testStep><con:properties/></con:testCase><con:testCase id="0d97ebd3-ebec-4aed-8b17-17426576fe67" failOnError="true" failTestCaseOnErrors="true" keepSession="false" maxResults="0" name="CountryIntPhoneCode TestCase" searchProperties="true"><con:settings/><con:testStep type="request" id="5f293a4c-4053-4d01-851f-db4ee196056e" name="CountryIntPhoneCode"><con:settings/><con:config xsi:type="con:RequestStep" xmlns:xsi="http://www.w3.org/2001/XMLSchema-instance"><con:interface>CountryInfoServiceSoapBinding</con:interface><con:operation>CountryIntPhoneCode</con:operation><con:request name="CountryIntPhoneCode" id="8ec6cee8-afd1-4343-9060-b50a4762c6ef"><con:settings/><con:encoding>UTF-8</con:encoding><con:endpoint>http://www.oorsprong.org/websamples.countryinfo/CountryInfoService.wso</con:endpoint><con:request><![CDATA[<soapenv:Envelope xmlns:soapenv="http://schemas.xmlsoap.org/soap/envelope/" xmlns:web="http://www.oorsprong.org/websamples.countryinfo">
   <soapenv:Header/>
   <soapenv:Body>
      <web:CountryIntPhoneCode>
         <web:sCountryISOCode>?</web:sCountryISOCode>
      </web:CountryIntPhoneCode>
   </soapenv:Body>
</soapenv:Envelope>]]></con:request><con:credentials><con:authType>No Authorization</con:authType></con:credentials><con:wsaConfig action="http://www.oorsprong.org/websamples.countryinfo/CountryInfoServiceSoapType/CountryIntPhoneCodeRequest"/></con:request></con:config></con:testStep><con:properties/></con:testCase><con:testCase id="6fe3b11b-a691-4126-a7c1-e92f6e9b0fbe" failOnError="true" failTestCaseOnErrors="true" keepSession="false" maxResults="0" name="CountryISOCode TestCase" searchProperties="true"><con:settings/><con:testStep type="request" id="cfc9a34d-d793-42c2-a08a-c450335b92f8" name="CountryISOCode"><con:settings/><con:config xsi:type="con:RequestStep" xmlns:xsi="http://www.w3.org/2001/XMLSchema-instance"><con:interface>CountryInfoServiceSoapBinding</con:interface><con:operation>CountryISOCode</con:operation><con:request name="CountryISOCode" id="52a06a7d-03a5-46a1-915f-b63fb51e0891"><con:settings/><con:encoding>UTF-8</con:encoding><con:endpoint>http://www.oorsprong.org/websamples.countryinfo/CountryInfoService.wso</con:endpoint><con:request><![CDATA[<soapenv:Envelope xmlns:soapenv="http://schemas.xmlsoap.org/soap/envelope/" xmlns:web="http://www.oorsprong.org/websamples.countryinfo">
   <soapenv:Header/>
   <soapenv:Body>
      <web:CountryISOCode>
         <web:sCountryName>?</web:sCountryName>
      </web:CountryISOCode>
   </soapenv:Body>
</soapenv:Envelope>]]></con:request><con:credentials><con:authType>No Authorization</con:authType></con:credentials><con:wsaConfig action="http://www.oorsprong.org/websamples.countryinfo/CountryInfoServiceSoapType/CountryISOCodeRequest"/></con:request></con:config></con:testStep><con:properties/></con:testCase><con:testCase id="f06eda8a-8fe7-49ad-9097-191a658e4f30" failOnError="true" failTestCaseOnErrors="true" keepSession="false" maxResults="0" name="CountryName TestCase" searchProperties="true"><con:settings/><con:testStep type="request" id="27c90740-6df3-4aab-bb5b-35d3921ba87b" name="CountryName"><con:settings/><con:config xsi:type="con:RequestStep" xmlns:xsi="http://www.w3.org/2001/XMLSchema-instance"><con:interface>CountryInfoServiceSoapBinding</con:interface><con:operation>CountryName</con:operation><con:request name="CountryName" id="5f71d185-8ccd-49a0-ad21-6409ce915d72"><con:settings/><con:encoding>UTF-8</con:encoding><con:endpoint>http://www.oorsprong.org/websamples.countryinfo/CountryInfoService.wso</con:endpoint><con:request><![CDATA[<soapenv:Envelope xmlns:soapenv="http://schemas.xmlsoap.org/soap/envelope/" xmlns:web="http://www.oorsprong.org/websamples.countryinfo">
   <soapenv:Header/>
   <soapenv:Body>
      <web:CountryName>
         <web:sCountryISOCode>?</web:sCountryISOCode>
      </web:CountryName>
   </soapenv:Body>
</soapenv:Envelope>]]></con:request><con:credentials><con:authType>No Authorization</con:authType></con:credentials><con:wsaConfig action="http://www.oorsprong.org/websamples.countryinfo/CountryInfoServiceSoapType/CountryNameRequest"/></con:request></con:config></con:testStep><con:properties/></con:testCase><con:testCase id="36197164-12b2-4f0d-9d3d-449ceda681cf" failOnError="true" failTestCaseOnErrors="true" keepSession="false" maxResults="0" name="CurrencyName TestCase" searchProperties="true"><con:settings/><con:testStep type="request" id="657c4277-c5c4-4eac-9fa3-ae9db127bd83" name="CurrencyName"><con:settings/><con:config xsi:type="con:RequestStep" xmlns:xsi="http://www.w3.org/2001/XMLSchema-instance"><con:interface>CountryInfoServiceSoapBinding</con:interface><con:operation>CurrencyName</con:operation><con:request name="CurrencyName" id="b78ccdfe-2c75-4fa2-ab0b-1551085f1347"><con:settings/><con:encoding>UTF-8</con:encoding><con:endpoint>http://www.oorsprong.org/websamples.countryinfo/CountryInfoService.wso</con:endpoint><con:request><![CDATA[<soapenv:Envelope xmlns:soapenv="http://schemas.xmlsoap.org/soap/envelope/" xmlns:web="http://www.oorsprong.org/websamples.countryinfo">
   <soapenv:Header/>
   <soapenv:Body>
      <web:CurrencyName>
         <web:sCurrencyISOCode>?</web:sCurrencyISOCode>
      </web:CurrencyName>
   </soapenv:Body>
</soapenv:Envelope>]]></con:request><con:credentials><con:authType>No Authorization</con:authType></con:credentials><con:wsaConfig action="http://www.oorsprong.org/websamples.countryinfo/CountryInfoServiceSoapType/CurrencyNameRequest"/></con:request></con:config></con:testStep><con:properties/></con:testCase><con:testCase id="063ec4f5-4f81-4722-aec8-f6180388453b" failOnError="true" failTestCaseOnErrors="true" keepSession="false" maxResults="0" name="FullCountryInfo TestCase" searchProperties="true"><con:settings/><con:testStep type="request" id="4de9c5d0-5cfe-4c7f-92c5-c2d80677e7b4" name="FullCountryInfo"><con:settings/><con:config xsi:type="con:RequestStep" xmlns:xsi="http://www.w3.org/2001/XMLSchema-instance"><con:interface>CountryInfoServiceSoapBinding</con:interface><con:operation>FullCountryInfo</con:operation><con:request name="FullCountryInfo" id="2411906a-eb09-41c5-9757-69d236bd6544"><con:settings/><con:encoding>UTF-8</con:encoding><con:endpoint>http://www.oorsprong.org/websamples.countryinfo/CountryInfoService.wso</con:endpoint><con:request><![CDATA[<soapenv:Envelope xmlns:soapenv="http://schemas.xmlsoap.org/soap/envelope/" xmlns:web="http://www.oorsprong.org/websamples.countryinfo">
   <soapenv:Header/>
   <soapenv:Body>
      <web:FullCountryInfo>
         <web:sCountryISOCode>?</web:sCountryISOCode>
      </web:FullCountryInfo>
   </soapenv:Body>
</soapenv:Envelope>]]></con:request><con:credentials><con:authType>No Authorization</con:authType></con:credentials><con:wsaConfig action="http://www.oorsprong.org/websamples.countryinfo/CountryInfoServiceSoapType/FullCountryInfoRequest"/></con:request></con:config></con:testStep><con:properties/></con:testCase><con:testCase id="0d1df02b-7a60-4e9d-9e98-960f8faf546d" failOnError="true" failTestCaseOnErrors="true" keepSession="false" maxResults="0" name="FullCountryInfoAllCountries TestCase" searchProperties="true"><con:settings/><con:testStep type="request" id="e2ebbc50-325e-4af2-9700-b6659de44283" name="FullCountryInfoAllCountries"><con:settings/><con:config xsi:type="con:RequestStep" xmlns:xsi="http://www.w3.org/2001/XMLSchema-instance"><con:interface>CountryInfoServiceSoapBinding</con:interface><con:operation>FullCountryInfoAllCountries</con:operation><con:request name="FullCountryInfoAllCountries" id="551b2fd4-b811-4809-8ca9-df4fa591714a"><con:settings/><con:encoding>UTF-8</con:encoding><con:endpoint>http://www.oorsprong.org/websamples.countryinfo/CountryInfoService.wso</con:endpoint><con:request><![CDATA[<soapenv:Envelope xmlns:soapenv="http://schemas.xmlsoap.org/soap/envelope/" xmlns:web="http://www.oorsprong.org/websamples.countryinfo">
   <soapenv:Header/>
   <soapenv:Body>
      <web:FullCountryInfoAllCountries/>
   </soapenv:Body>
</soapenv:Envelope>]]></con:request><con:credentials><con:authType>No Authorization</con:authType></con:credentials><con:wsaConfig action="http://www.oorsprong.org/websamples.countryinfo/CountryInfoServiceSoapType/FullCountryInfoAllCountriesRequest"/></con:request></con:config></con:testStep><con:properties/></con:testCase><con:testCase id="d01633b2-8553-4044-9102-9db02a8353c5" failOnError="true" failTestCaseOnErrors="true" keepSession="false" maxResults="0" name="LanguageISOCode TestCase" searchProperties="true"><con:settings/><con:testStep type="request" id="a1ee5e09-8adf-48ec-ad90-9ea7063760e2" name="LanguageISOCode"><con:settings/><con:config xsi:type="con:RequestStep" xmlns:xsi="http://www.w3.org/2001/XMLSchema-instance"><con:interface>CountryInfoServiceSoapBinding</con:interface><con:operation>LanguageISOCode</con:operation><con:request name="LanguageISOCode" id="55831fc4-84f3-4c5c-8df6-5e68f6d8971f"><con:settings/><con:encoding>UTF-8</con:encoding><con:endpoint>http://www.oorsprong.org/websamples.countryinfo/CountryInfoService.wso</con:endpoint><con:request><![CDATA[<soapenv:Envelope xmlns:soapenv="http://schemas.xmlsoap.org/soap/envelope/" xmlns:web="http://www.oorsprong.org/websamples.countryinfo">
   <soapenv:Header/>
   <soapenv:Body>
      <web:LanguageISOCode>
         <web:sLanguageName>?</web:sLanguageName>
      </web:LanguageISOCode>
   </soapenv:Body>
</soapenv:Envelope>]]></con:request><con:credentials><con:authType>No Authorization</con:authType></con:credentials><con:wsaConfig action="http://www.oorsprong.org/websamples.countryinfo/CountryInfoServiceSoapType/LanguageISOCodeRequest"/></con:request></con:config></con:testStep><con:properties/></con:testCase><con:testCase id="399672e2-c4a9-4817-aad8-e1cf78b6d9f9" failOnError="true" failTestCaseOnErrors="true" keepSession="false" maxResults="0" name="LanguageName TestCase" searchProperties="true"><con:settings/><con:testStep type="request" id="fe255419-8a43-497f-a49a-25739711bf50" name="LanguageName"><con:settings/><con:config xsi:type="con:RequestStep" xmlns:xsi="http://www.w3.org/2001/XMLSchema-instance"><con:interface>CountryInfoServiceSoapBinding</con:interface><con:operation>LanguageName</con:operation><con:request name="LanguageName" id="deb76b5f-c96e-462c-b438-9bfb3ff01abf"><con:settings/><con:encoding>UTF-8</con:encoding><con:endpoint>http://www.oorsprong.org/websamples.countryinfo/CountryInfoService.wso</con:endpoint><con:request><![CDATA[<soapenv:Envelope xmlns:soapenv="http://schemas.xmlsoap.org/soap/envelope/" xmlns:web="http://www.oorsprong.org/websamples.countryinfo">
   <soapenv:Header/>
   <soapenv:Body>
      <web:LanguageName>
         <web:sISOCode>?</web:sISOCode>
      </web:LanguageName>
   </soapenv:Body>
</soapenv:Envelope>]]></con:request><con:credentials><con:authType>No Authorization</con:authType></con:credentials><con:wsaConfig action="http://www.oorsprong.org/websamples.countryinfo/CountryInfoServiceSoapType/LanguageNameRequest"/></con:request></con:config></con:testStep><con:properties/></con:testCase><con:testCase id="c0abe3f1-a2d3-4a2f-ba40-734c85095a15" failOnError="true" failTestCaseOnErrors="true" keepSession="false" maxResults="0" name="ListOfContinentsByCode TestCase" searchProperties="true"><con:settings/><con:testStep type="request" id="9bd49460-fb1f-4977-a67f-1f0df159697c" name="ListOfContinentsByCode"><con:settings/><con:config xsi:type="con:RequestStep" xmlns:xsi="http://www.w3.org/2001/XMLSchema-instance"><con:interface>CountryInfoServiceSoapBinding</con:interface><con:operation>ListOfContinentsByCode</con:operation><con:request name="ListOfContinentsByCode" id="08c347cd-2864-411f-abec-b4f19141a968"><con:settings/><con:encoding>UTF-8</con:encoding><con:endpoint>http://www.oorsprong.org/websamples.countryinfo/CountryInfoService.wso</con:endpoint><con:request><![CDATA[<soapenv:Envelope xmlns:soapenv="http://schemas.xmlsoap.org/soap/envelope/" xmlns:web="http://www.oorsprong.org/websamples.countryinfo">
   <soapenv:Header/>
   <soapenv:Body>
      <web:ListOfContinentsByCode/>
   </soapenv:Body>
</soapenv:Envelope>]]></con:request><con:credentials><con:authType>No Authorization</con:authType></con:credentials><con:wsaConfig action="http://www.oorsprong.org/websamples.countryinfo/CountryInfoServiceSoapType/ListOfContinentsByCodeRequest"/></con:request></con:config></con:testStep><con:properties/></con:testCase><con:testCase id="2a68315d-0a5d-4b6f-b23a-6cba0584fd81" failOnError="true" failTestCaseOnErrors="true" keepSession="false" maxResults="0" name="ListOfContinentsByName TestCase" searchProperties="true"><con:settings/><con:testStep type="request" id="fd8398f3-84fd-49fb-a6ac-bb3af39c749e" name="ListOfContinentsByName"><con:settings/><con:config xsi:type="con:RequestStep" xmlns:xsi="http://www.w3.org/2001/XMLSchema-instance"><con:interface>CountryInfoServiceSoapBinding</con:interface><con:operation>ListOfContinentsByName</con:operation><con:request name="ListOfContinentsByName" id="7290d5ce-35f3-4d3e-96f5-7041457c0abc"><con:settings/><con:encoding>UTF-8</con:encoding><con:endpoint>http://www.oorsprong.org/websamples.countryinfo/CountryInfoService.wso</con:endpoint><con:request><![CDATA[<soapenv:Envelope xmlns:soapenv="http://schemas.xmlsoap.org/soap/envelope/" xmlns:web="http://www.oorsprong.org/websamples.countryinfo">
   <soapenv:Header/>
   <soapenv:Body>
      <web:ListOfContinentsByName/>
   </soapenv:Body>
</soapenv:Envelope>]]></con:request><con:credentials><con:authType>No Authorization</con:authType></con:credentials><con:wsaConfig action="http://www.oorsprong.org/websamples.countryinfo/CountryInfoServiceSoapType/ListOfContinentsByNameRequest"/></con:request></con:config></con:testStep><con:properties/></con:testCase><con:testCase id="307ca28b-dd62-44b9-ae49-cff65ec79c61" failOnError="true" failTestCaseOnErrors="true" keepSession="false" maxResults="0" name="ListOfCountryNamesByCode TestCase" searchProperties="true"><con:settings/><con:testStep type="request" id="d0ce790e-f00c-4f0b-8412-b954f3e66288" name="ListOfCountryNamesByCode"><con:settings/><con:config xsi:type="con:RequestStep" xmlns:xsi="http://www.w3.org/2001/XMLSchema-instance"><con:interface>CountryInfoServiceSoapBinding</con:interface><con:operation>ListOfCountryNamesByCode</con:operation><con:request name="ListOfCountryNamesByCode" id="3d534e96-6460-443c-bf23-306e0306240c"><con:settings/><con:encoding>UTF-8</con:encoding><con:endpoint>http://www.oorsprong.org/websamples.countryinfo/CountryInfoService.wso</con:endpoint><con:request><![CDATA[<soapenv:Envelope xmlns:soapenv="http://schemas.xmlsoap.org/soap/envelope/" xmlns:web="http://www.oorsprong.org/websamples.countryinfo">
   <soapenv:Header/>
   <soapenv:Body>
      <web:ListOfCountryNamesByCode/>
   </soapenv:Body>
</soapenv:Envelope>]]></con:request><con:credentials><con:authType>No Authorization</con:authType></con:credentials><con:wsaConfig action="http://www.oorsprong.org/websamples.countryinfo/CountryInfoServiceSoapType/ListOfCountryNamesByCodeRequest"/></con:request></con:config></con:testStep><con:properties/></con:testCase><con:testCase id="30034caf-d775-4a37-829a-cccd9271db9a" failOnError="true" failTestCaseOnErrors="true" keepSession="false" maxResults="0" name="ListOfCountryNamesByName TestCase" searchProperties="true"><con:settings/><con:testStep type="request" id="1cc5c91c-4fca-427c-bd54-2206f95bddbe" name="ListOfCountryNamesByName"><con:settings/><con:config xsi:type="con:RequestStep" xmlns:xsi="http://www.w3.org/2001/XMLSchema-instance"><con:interface>CountryInfoServiceSoapBinding</con:interface><con:operation>ListOfCountryNamesByName</con:operation><con:request name="ListOfCountryNamesByName" id="7bf308ab-430d-4ed4-a5fb-e243b7b03df8"><con:settings/><con:encoding>UTF-8</con:encoding><con:endpoint>http://www.oorsprong.org/websamples.countryinfo/CountryInfoService.wso</con:endpoint><con:request><![CDATA[<soapenv:Envelope xmlns:soapenv="http://schemas.xmlsoap.org/soap/envelope/" xmlns:web="http://www.oorsprong.org/websamples.countryinfo">
   <soapenv:Header/>
   <soapenv:Body>
      <web:ListOfCountryNamesByName/>
   </soapenv:Body>
</soapenv:Envelope>]]></con:request><con:credentials><con:authType>No Authorization</con:authType></con:credentials><con:wsaConfig action="http://www.oorsprong.org/websamples.countryinfo/CountryInfoServiceSoapType/ListOfCountryNamesByNameRequest"/></con:request></con:config></con:testStep><con:properties/></con:testCase><con:testCase id="ae6d6a3e-e151-4f20-aab5-9344345de537" failOnError="true" failTestCaseOnErrors="true" keepSession="false" maxResults="0" name="ListOfCountryNamesGroupedByContinent TestCase" searchProperties="true"><con:settings/><con:testStep type="request" id="6c7cfe8e-b4fa-42a2-b026-51993bb364df" name="ListOfCountryNamesGroupedByContinent"><con:settings/><con:config xsi:type="con:RequestStep" xmlns:xsi="http://www.w3.org/2001/XMLSchema-instance"><con:interface>CountryInfoServiceSoapBinding</con:interface><con:operation>ListOfCountryNamesGroupedByContinent</con:operation><con:request name="ListOfCountryNamesGroupedByContinent" id="e9160649-2014-4fa4-8b43-c48964b5a2a6"><con:settings/><con:encoding>UTF-8</con:encoding><con:endpoint>http://www.oorsprong.org/websamples.countryinfo/CountryInfoService.wso</con:endpoint><con:request><![CDATA[<soapenv:Envelope xmlns:soapenv="http://schemas.xmlsoap.org/soap/envelope/" xmlns:web="http://www.oorsprong.org/websamples.countryinfo">
   <soapenv:Header/>
   <soapenv:Body>
      <web:ListOfCountryNamesGroupedByContinent/>
   </soapenv:Body>
</soapenv:Envelope>]]></con:request><con:credentials><con:authType>No Authorization</con:authType></con:credentials><con:wsaConfig action="http://www.oorsprong.org/websamples.countryinfo/CountryInfoServiceSoapType/ListOfCountryNamesGroupedByContinentRequest"/></con:request></con:config></con:testStep><con:properties/></con:testCase><con:testCase id="786ecb20-ba16-4fd6-ac8b-bfc96f26a132" failOnError="true" failTestCaseOnErrors="true" keepSession="false" maxResults="0" name="ListOfCurrenciesByCode TestCase" searchProperties="true"><con:settings/><con:testStep type="request" id="41174f15-0c26-4064-becd-49b2157e50db" name="ListOfCurrenciesByCode"><con:settings/><con:config xsi:type="con:RequestStep" xmlns:xsi="http://www.w3.org/2001/XMLSchema-instance"><con:interface>CountryInfoServiceSoapBinding</con:interface><con:operation>ListOfCurrenciesByCode</con:operation><con:request name="ListOfCurrenciesByCode" id="b3b430ad-cb31-4511-9ed4-04467c3dc24f"><con:settings/><con:encoding>UTF-8</con:encoding><con:endpoint>http://www.oorsprong.org/websamples.countryinfo/CountryInfoService.wso</con:endpoint><con:request><![CDATA[<soapenv:Envelope xmlns:soapenv="http://schemas.xmlsoap.org/soap/envelope/" xmlns:web="http://www.oorsprong.org/websamples.countryinfo">
   <soapenv:Header/>
   <soapenv:Body>
      <web:ListOfCurrenciesByCode/>
   </soapenv:Body>
</soapenv:Envelope>]]></con:request><con:credentials><con:authType>No Authorization</con:authType></con:credentials><con:wsaConfig action="http://www.oorsprong.org/websamples.countryinfo/CountryInfoServiceSoapType/ListOfCurrenciesByCodeRequest"/></con:request></con:config></con:testStep><con:properties/></con:testCase><con:testCase id="c95e4862-7b8c-4098-8fde-11babe6a57f5" failOnError="true" failTestCaseOnErrors="true" keepSession="false" maxResults="0" name="ListOfCurrenciesByName TestCase" searchProperties="true"><con:settings/><con:testStep type="request" id="12f5db2a-3776-47fe-ba45-bd284aff700b" name="ListOfCurrenciesByName"><con:settings/><con:config xsi:type="con:RequestStep" xmlns:xsi="http://www.w3.org/2001/XMLSchema-instance"><con:interface>CountryInfoServiceSoapBinding</con:interface><con:operation>ListOfCurrenciesByName</con:operation><con:request name="ListOfCurrenciesByName" id="bdee1e11-0dd5-424d-92e7-dcc0d9e2e8e0"><con:settings/><con:encoding>UTF-8</con:encoding><con:endpoint>http://www.oorsprong.org/websamples.countryinfo/CountryInfoService.wso</con:endpoint><con:request><![CDATA[<soapenv:Envelope xmlns:soapenv="http://schemas.xmlsoap.org/soap/envelope/" xmlns:web="http://www.oorsprong.org/websamples.countryinfo">
   <soapenv:Header/>
   <soapenv:Body>
      <web:ListOfCurrenciesByName/>
   </soapenv:Body>
</soapenv:Envelope>]]></con:request><con:credentials><con:authType>No Authorization</con:authType></con:credentials><con:wsaConfig action="http://www.oorsprong.org/websamples.countryinfo/CountryInfoServiceSoapType/ListOfCurrenciesByNameRequest"/></con:request></con:config></con:testStep><con:properties/></con:testCase><con:testCase id="b3397a6c-fc4f-43d6-8070-dfd6302c1b12" failOnError="true" failTestCaseOnErrors="true" keepSession="false" maxResults="0" name="ListOfLanguagesByCode TestCase" searchProperties="true"><con:settings/><con:testStep type="request" id="d0031546-50e7-4e11-9e7e-c656aa92925a" name="ListOfLanguagesByCode"><con:settings/><con:config xsi:type="con:RequestStep" xmlns:xsi="http://www.w3.org/2001/XMLSchema-instance"><con:interface>CountryInfoServiceSoapBinding</con:interface><con:operation>ListOfLanguagesByCode</con:operation><con:request name="ListOfLanguagesByCode" id="1b041759-91a1-44b8-89eb-5294ed5f5981"><con:settings/><con:encoding>UTF-8</con:encoding><con:endpoint>http://www.oorsprong.org/websamples.countryinfo/CountryInfoService.wso</con:endpoint><con:request><![CDATA[<soapenv:Envelope xmlns:soapenv="http://schemas.xmlsoap.org/soap/envelope/" xmlns:web="http://www.oorsprong.org/websamples.countryinfo">
   <soapenv:Header/>
   <soapenv:Body>
      <web:ListOfLanguagesByCode/>
   </soapenv:Body>
</soapenv:Envelope>]]></con:request><con:credentials><con:authType>No Authorization</con:authType></con:credentials><con:wsaConfig action="http://www.oorsprong.org/websamples.countryinfo/CountryInfoServiceSoapType/ListOfLanguagesByCodeRequest"/></con:request></con:config></con:testStep><con:properties/></con:testCase><con:testCase id="32bcfa57-9846-442e-a166-58984cb164a5" failOnError="true" failTestCaseOnErrors="true" keepSession="false" maxResults="0" name="ListOfLanguagesByName TestCase" searchProperties="true"><con:settings/><con:testStep type="request" id="91a6244e-cbf7-4061-a913-cd373d6c0c4a" name="ListOfLanguagesByName"><con:settings/><con:config xsi:type="con:RequestStep" xmlns:xsi="http://www.w3.org/2001/XMLSchema-instance"><con:interface>CountryInfoServiceSoapBinding</con:interface><con:operation>ListOfLanguagesByName</con:operation><con:request name="ListOfLanguagesByName" id="cbb2149b-5818-489d-a33a-636cb03962a1"><con:settings/><con:encoding>UTF-8</con:encoding><con:endpoint>http://www.oorsprong.org/websamples.countryinfo/CountryInfoService.wso</con:endpoint><con:request><![CDATA[<soapenv:Envelope xmlns:soapenv="http://schemas.xmlsoap.org/soap/envelope/" xmlns:web="http://www.oorsprong.org/websamples.countryinfo">
   <soapenv:Header/>
   <soapenv:Body>
      <web:ListOfLanguagesByName/>
   </soapenv:Body>
</soapenv:Envelope>]]></con:request><con:credentials><con:authType>No Authorization</con:authType></con:credentials><con:wsaConfig action="http://www.oorsprong.org/websamples.countryinfo/CountryInfoServiceSoapType/ListOfLanguagesByNameRequest"/></con:request></con:config></con:testStep><con:properties/></con:testCase><con:properties/></con:testSuite><con:properties/><con:wssContainer/><con:oAuth2ProfileContainer/><con:oAuth1ProfileContainer/><con:sensitiveInformation/></con:soapui-project>